purelypdb/__init__.py
purelypdb/dbgold.py
purelypdb/dbi.py
purelypdb/fpo.py
purelypdb/gdata.py
purelypdb/info.py
purelypdb/omap.py
purelypdb/pe.py
purelypdb/peinfo.py
purelypdb/postfix_eval.py
purelypdb/struct_parser.py
purelypdb/symlookup.py
purelypdb/tpi.py
purelypdb/undecorate.py
purelypdb/undname.py
purelypdb-1.0.0.dist-info/licenses/LICENSE
purelypdb-1.0.0.dist-info/METADATA
purelypdb-1.0.0.dist-info/WHEEL
purelypdb-1.0.0.dist-info/top_level.txt
purelypdb-1.0.0.dist-info/RECORD
