Metadata-Version: 2.4
Name: purelypdb
Version: 1.0.0
Summary: Cross-platform Python parser for Microsoft PDB files with no external dependencies
Author: saileaxh
License: GPL-2.0-only
Project-URL: Homepage, https://github.com/dejavu-secure/PurelyPDB
Project-URL: Repository, https://github.com/dejavu-secure/PurelyPDB
Keywords: pdb,debug,symbols,microsoft,windows,parsing
Classifier: Development Status :: 4 - Beta
Classifier: Intended Audience :: Developers
Classifier: Operating System :: OS Independent
Classifier: Programming Language :: Python :: 3
Classifier: Programming Language :: Python :: 3.7
Classifier: Programming Language :: Python :: 3.8
Classifier: Programming Language :: Python :: 3.9
Classifier: Programming Language :: Python :: 3.10
Classifier: Programming Language :: Python :: 3.11
Classifier: Programming Language :: Python :: 3.12
Classifier: Topic :: Software Development :: Debuggers
Classifier: Topic :: Software Development :: Disassemblers
Requires-Python: >=3.7
License-File: LICENSE
Provides-Extra: dev
Requires-Dist: pytest; extra == "dev"
Requires-Dist: build; extra == "dev"
Requires-Dist: twine; extra == "dev"
Dynamic: license-file
